ckey/__init__.py
ckey/main.py
ckey/utils/__init__.py
ckey/utils/aggregators.py
ckey/utils/api.py
ckey/utils/constants.py
ckey/utils/formatters.py
ckey-1.0.0a1.dist-info/LICENSE
ckey-1.0.0a1.dist-info/METADATA
ckey-1.0.0a1.dist-info/WHEEL
ckey-1.0.0a1.dist-info/top_level.txt
ckey-1.0.0a1.dist-info/RECORD
