Metadata-Version: 2.1
Name: ckey
Version: 1.0.0a1
Summary: OpenFEC API client for researching the political spending of executives
Home-page: https://github.com/justin-g-davis/ckey
Author: Justin G. Davis
Classifier: Development Status :: 5 - Production/Stable
Classifier: Intended Audience :: Science/Research
Classifier: License :: OSI Approved :: MIT License
Classifier: Programming Language :: Python :: 3.6
Classifier: Programming Language :: Python :: 3.7
Classifier: Programming Language :: Python :: 3.8
Classifier: Programming Language :: Python :: 3.9
Requires-Python: >=3.6
License-File: LICENSE
Requires-Dist: pandas>=2.0.0
Requires-Dist: requests>=2.31.0
Requires-Dist: ThreadPoolExecutorPlus>=0.2.2
